torch_onnx/__init__.py
torch_onnx/_analysis.py
torch_onnx/_building.py
torch_onnx/_capture_strategies.py
torch_onnx/_core.py
torch_onnx/_core_test.py
torch_onnx/_decomp.py
torch_onnx/_dispatching.py
torch_onnx/_fx_passes.py
torch_onnx/_ir_passes.py
torch_onnx/_isolated.py
torch_onnx/_onnx_program.py
torch_onnx/_patch.py
torch_onnx/_registration.py
torch_onnx/_reporting.py
torch_onnx/_schemas.py
torch_onnx/_schemas_test.py
torch_onnx/_tensors.py
torch_onnx/_tensors_test.py
torch_onnx/_testing.py
torch_onnx/_torchscript_converter.py
torch_onnx/_verification.py
torch_onnx/errors.py
torch_onnx/bin/convert.py
torch_onnx/tools/diff_model.py
torch_onnx-0.1.25.dist-info/LICENSE
torch_onnx-0.1.25.dist-info/METADATA
torch_onnx-0.1.25.dist-info/WHEEL
torch_onnx-0.1.25.dist-info/entry_points.txt
torch_onnx-0.1.25.dist-info/top_level.txt
torch_onnx-0.1.25.dist-info/RECORD
