Metadata-Version: 2.1
Name: torch-onnx
Version: 0.1.25
Summary: Experimental tools for converting PyTorch models to ONNX
Author-email: Justin Chu <justinchu@microsoft.com>
License: MIT License
Project-URL: Repository, https://github.com/justinchuby/torch-onnx
Keywords: onnx,pytorch,converter,convertion,exporter
Classifier: Development Status :: 3 - Alpha
Classifier: Environment :: Console
Classifier: Intended Audience :: Developers
Classifier: Operating System :: POSIX
Classifier: Operating System :: MacOS :: MacOS X
Classifier: Operating System :: Microsoft :: Windows
Classifier: Programming Language :: Python :: 3.8
Classifier: Programming Language :: Python :: 3.9
Classifier: Programming Language :: Python :: 3.10
Classifier: Programming Language :: Python :: 3.11
Classifier: Programming Language :: Python :: 3.12
Classifier: License :: OSI Approved :: MIT License
Requires-Python: >=3.8
License-File: LICENSE
Requires-Dist: torch >=2.1
Requires-Dist: onnxscript >=0.1.0.dev20240831
Requires-Dist: onnx >=1.16
Requires-Dist: typing-extensions
Requires-Dist: packaging
